longhow/__init__.py
longhow/longhow.py
longhow-0.1.0.dist-info/WHEEL
longhow-0.1.0.dist-info/METADATA
longhow-0.1.0.dist-info/RECORD
